fa/fa.v
module FA(x, y, cin, s, cout);
	input x, y, cin;
	output s, cout;

	assign s = x & y & cin | ~x & ~y & cin | x & ~y & ~cin | ~x & y & ~cin;
	assign cout = x & y | y & cin | cin & x;
endmodule

module TEST;
	parameter BIT = 3;
	
	reg [BIT-1:0] a;
	wire s, cout;
	
	initial begin
		$dumpfile("test.vcd");
		$dumpvars(0, TEST);
		$monitor ("%t: %b + %b + %b = %b%b", $time, a[2], a[1], a[0], cout, s);
		
		a <= 0;
		repeat(2**BIT-1) begin
			#10 a <= a + 1;
		end
		#10 $finish;
	end
	
	FA fatest (a[1], a[0], a[2], s, cout);
endmodule

fa/test.vcd
$date
	Wed May 21 16:40:19 2014
$end
$version
	Icarus Verilog
$end
$timescale
	1s
$end
$scope module TEST $end
$var wire 1 ! cout $end
$var wire 1 " s $end
$var reg 3 # a [2:0] $end
$scope module fatest $end
$var wire 1 $ cin $end
$var wire 1 ! cout $end
$var wire 1 " s $end
$var wire 1 % x $end
$var wire 1 & y $end
$upscope $end
$upscope $end
$enddefinitions $end
#0
$dumpvars
0&
0%
0$
b0 #
0"
0!
$end
#10
1"
1&
b1 #
#20
1"
1%
0&
b10 #
#30
0"
1!
1&
b11 #
#40
1"
0!
0%
0&
1$
b100 #
#50
0"
1!
1&
b101 #
#60
1%
0&
b110 #
#70
1"
1&
b111 #
